satel_ethm/__init__.py
satel_ethm/async_api.py
satel_ethm/py.typed
satel_ethm-0.0.0.dist-info/METADATA
satel_ethm-0.0.0.dist-info/WHEEL
satel_ethm-0.0.0.dist-info/RECORD
